htmlscraper/__init__.py
htmlscraper/common/__init__.py
htmlscraper/common/simple_sqlite.py
htmlscraper/common/trimmers.py
htmlscraper/data/__init__.py
htmlscraper/data/abstraction/__init__.py
htmlscraper/data/abstraction/abstract_attachment.py
htmlscraper/data/abstraction/abstract_page.py
htmlscraper/data/abstraction/abstract_posting.py
htmlscraper/data/abstraction/abstract_site.py
htmlscraper/data/abstraction/user.py
htmlscraper/data/content/__init__.py
htmlscraper/data/content/comment.py
htmlscraper/data/content/content.py
htmlscraper/data/content/file.py
htmlscraper/data/simple_html/__init__.py
htmlscraper/data/simple_html/simple_html_page.py
htmlscraper/data/simple_html/simple_html_posting.py
htmlscraper/data/simple_html/simple_html_site.py
htmlscraper/data/user/__init__.py
htmlscraper/data/user/author.py
htmlscraper/data/user/business_owner.py
htmlscraper/data/user/candidate.py
htmlscraper/data/user/utils.py
htmlscraper/preprocessing/__init__.py
htmlscraper/preprocessing/text_trimming.py
htmlscraper/preprocessing/train_sentencepiece.py
unittests/__init__.py
unittests/data/__init__.py
unittests/data/simple_html/__init__.py
unittests/data/simple_html/test_simple_html_page.py
htmlscraper-0.0.3.dist-info/LICENSE
htmlscraper-0.0.3.dist-info/METADATA
htmlscraper-0.0.3.dist-info/WHEEL
htmlscraper-0.0.3.dist-info/top_level.txt
htmlscraper-0.0.3.dist-info/RECORD
